askandyz_house_location_analyst/__init__.py
askandyz_house_location_analyst/__main__.py
askandyz_house_location_analyst/cache.py
askandyz_house_location_analyst/config.py
askandyz_house_location_analyst/llm_tool.py
askandyz_house_location_analyst/localtion_analyzer.py
askandyz_house_location_analyst/map_client.py
askandyz_house_location_analyst/map_tool.py
askandyz_house_location_analyst/modal.py
askandyz_house_location_analyst/report_generator.py
askandyz_house_location_analyst/templates/community.hbs
askandyz_house_location_analyst/templates/comparison.hbs
askandyz_house_location_analyst/tool_cache.db
askandyz_house_location_analyst-1.0.6.dist-info/WHEEL
askandyz_house_location_analyst-1.0.6.dist-info/entry_points.txt
askandyz_house_location_analyst-1.0.6.dist-info/METADATA
askandyz_house_location_analyst-1.0.6.dist-info/RECORD
