Metadata-Version: 2.3
Name: askandyz-house-location-analyst
Version: 1.0.6
Summary: 房产选址分析师
Author: Andy Zhang
Author-email: Andy Zhang <andyz@cdata.com>
Requires-Dist: fastmcp>=2.13.3
Requires-Dist: pybars3>=0.9.7
Requires-Dist: sqlalchemy>=2.0.44
Requires-Python: >=3.12
